[
  {
    "full_name": "tremorlabs/tremor",
    "stargazers_count": 3301,
    "open_issues_count": 19,
    "forks_count": 48
  },
  {
    "full_name": "turbot/steampipe",
    "stargazers_count": 3742,
    "open_issues_count": 260,
    "forks_count": 128
  },
  {
    "full_name": "parvardegr/sharing",
    "stargazers_count": 1015,
    "open_issues_count": 1,
    "forks_count": 37
  },
  {
    "full_name": "kolofordjango/kolo",
    "stargazers_count": 216,
    "open_issues_count": 14,
    "forks_count": 7
  },
  {
    "full_name": "brandtbucher/specialist",
    "stargazers_count": 310,
    "open_issues_count": 0,
    "forks_count": 7
  },
  {
    "full_name": "charliermarsh/ruff",
    "stargazers_count": 2136,
    "open_issues_count": 41,
    "forks_count": 41
  },
  {
    "full_name": "TheAlgorithms/Python",
    "stargazers_count": 146804,
    "open_issues_count": 252,
    "forks_count": 37556
  },
  {
    "full_name": "adamghill/django-fbv",
    "stargazers_count": 34,
    "open_issues_count": 0,
    "forks_count": 0
  },
  {
    "full_name": "jefftriplett/django-startproject",
    "stargazers_count": 74,
    "open_issues_count": 1,
    "forks_count": 6
  },
  {
    "full_name": "pallets/quart",
    "stargazers_count": 1400,
    "open_issues_count": 7,
    "forks_count": 82
  },
  {
    "full_name": "jetpack-io/devbox",
    "stargazers_count": 3941,
    "open_issues_count": 42,
    "forks_count": 51
  },
  {
    "full_name": "pypa/hatch",
    "stargazers_count": 3101,
    "open_issues_count": 13,
    "forks_count": 139
  },
  {
    "full_name": "Kludex/gh-co-author",
    "stargazers_count": 6,
    "open_issues_count": 0,
    "forks_count": 0
  },
  {
    "full_name": "actions/github-script",
    "stargazers_count": 2795,
    "open_issues_count": 20,
    "forks_count": 290
  },
  {
    "full_name": "Opus10/django-pgtrigger",
    "stargazers_count": 344,
    "open_issues_count": 10,
    "forks_count": 16
  },
  {
    "full_name": "microsoft/AI-For-Beginners",
    "stargazers_count": 2771,
    "open_issues_count": 17,
    "forks_count": 540
  },
  {
    "full_name": "raimon49/pip-licenses",
    "stargazers_count": 203,
    "open_issues_count": 16,
    "forks_count": 27
  },
  {
    "full_name": "rtts/djhtml",
    "stargazers_count": 356,
    "open_issues_count": 5,
    "forks_count": 22
  },
  {
    "full_name": "Riverside-Healthcare/djLint",
    "stargazers_count": 196,
    "open_issues_count": 24,
    "forks_count": 26
  },
  {
    "full_name": "py-cov-action/python-coverage-comment-action",
    "stargazers_count": 12,
    "open_issues_count": 6,
    "forks_count": 9
  },
  {
    "full_name": "orgoro/coverage",
    "stargazers_count": 20,
    "open_issues_count": 5,
    "forks_count": 5
  },
  {
    "full_name": "moyix/fauxpilot",
    "stargazers_count": 6526,
    "open_issues_count": 24,
    "forks_count": 264
  },
  {
    "full_name": "shallwefootball/upload-s3-action",
    "stargazers_count": 78,
    "open_issues_count": 23,
    "forks_count": 82
  },
  {
    "full_name": "trpc/trpc",
    "stargazers_count": 13872,
    "open_issues_count": 75,
    "forks_count": 435
  },
  {
    "full_name": "jpsca/tcom",
    "stargazers_count": 32,
    "open_issues_count": 0,
    "forks_count": 1
  },
  {
    "full_name": "n3r4zzurr0/svg-spinners",
    "stargazers_count": 4293,
    "open_issues_count": 0,
    "forks_count": 340
  },
  {
    "full_name": "django-hijack/django-hijack",
    "stargazers_count": 1167,
    "open_issues_count": 8,
    "forks_count": 152
  },
  {
    "full_name": "urllib3/urllib3",
    "stargazers_count": 3165,
    "open_issues_count": 113,
    "forks_count": 994
  },
  {
    "full_name": "casey/just",
    "stargazers_count": 7305,
    "open_issues_count": 160,
    "forks_count": 218
  },
  {
    "full_name": "nithinmurali/pygsheets",
    "stargazers_count": 1361,
    "open_issues_count": 47,
    "forks_count": 199
  }
]